petal/__init__.py
petal/__main__.py
petal/cli.py
petal/exceptions.py
petal/grpc_services.py
petal/log.py
petal/protoc_gen_extract_streaming.py
petal-0.0.2.post2.dist-info/METADATA
petal-0.0.2.post2.dist-info/WHEEL
petal-0.0.2.post2.dist-info/entry_points.txt
petal-0.0.2.post2.dist-info/top_level.txt
petal-0.0.2.post2.dist-info/RECORD
