Metadata-Version: 2.1
Name: petal
Version: 0.0.2.post2
Summary: UNKNOWN
Home-page: https://github.com/orf/petal
Author: Tom Forbes
Author-email: tom@tomforb.es
License: MIT
Platform: UNKNOWN
Requires-Python: >=3.6
Requires-Dist: loguru
Requires-Dist: requests
Requires-Dist: grpcio
Requires-Dist: grpcio-tools
Requires-Dist: click
Requires-Dist: mypy-protobuf
